{
  "market.page_title": "插件市场",
  "market.toolbar.search_placeholder": "搜索插件",
  "market.toolbar.refresh": "刷新",
  "market.status.loading": "正在加载官方插件市场…",
  "market.status.loaded_network_format": "已从官方源加载 {0} 个插件。",
  "market.status.loaded_cache_format": "官方源不可用，已从缓存加载 {0} 个插件。原因：{1}",
  "market.status.load_failed_format": "加载插件市场失败：{0}",
  "market.status.installing_format": "正在下载并暂存插件“{0}”…",
  "market.status.install_success_format": "插件“{0}”已暂存完成，重启应用后生效。",
  "market.status.install_failed_format": "安装插件失败：{0}",
  "market.status.host_incompatible_format": "当前宿主版本过低，至少需要 {0}。",
  "market.list.empty": "插件市场尚未加载。",
  "market.list.no_results": "没有匹配的插件。",
  "market.card.subtitle_format": "{0} · v{1}",
  "market.card.loaded": "已加载",
  "market.card.pending_restart": "需重启",
  "market.detail.placeholder": "从左侧选择一个插件以查看详情。",
  "market.detail.author": "作者",
  "market.detail.version": "版本",
  "market.detail.api_version": "API 版本",
  "market.detail.min_host_version": "最低宿主版本",
  "market.detail.installed_version": "当前已安装版本",
  "market.detail.not_installed": "未安装",
  "market.detail.market_source": "市场源",
  "market.detail.homepage": "主页",
  "market.detail.repository": "仓库",
  "market.detail.release_notes": "发布说明",
  "market.detail.state.not_installed": "未安装",
  "market.detail.state.update_available": "可更新",
  "market.detail.state.installed": "已安装",
  "market.detail.unknown": "未知",
  "market.button.install": "安装",
  "market.button.update": "更新",
  "market.button.installed": "已安装",
  "market.button.installing": "安装中…"
}
